wilson/README.md
wilson/__init__.py
wilson/app.zip
wilson/catalogue.py
wilson/color.py
wilson/data.py
wilson/objects.py
wilson/parse.py
wilson/project.py
wilson/serialize.py
wilson/server.py
wilson/proto/__init__.py
wilson/proto/animatible_pb2.py
wilson/proto/camera_pb2.py
wilson/proto/color_pb2.py
wilson/proto/colormap_pb2.py
wilson/proto/graph_pb2.py
wilson/proto/interpolation_pb2.py
wilson/proto/line_pb2.py
wilson/proto/meta_pb2.py
wilson/proto/overlay_pb2.py
wilson/proto/path_pb2.py
wilson/proto/prism_pb2.py
wilson/proto/project_pb2.py
wilson/proto/properties_pb2.py
wilson/proto/sphere_pb2.py
wilson/proto/tube_pb2.py
wilson/proto/vector_pb2.py
wilson3d-0.4.1.dist-info/LICENSE
wilson3d-0.4.1.dist-info/METADATA
wilson3d-0.4.1.dist-info/WHEEL
wilson3d-0.4.1.dist-info/entry_points.txt
wilson3d-0.4.1.dist-info/top_level.txt
wilson3d-0.4.1.dist-info/RECORD
