Metadata-Version: 2.1
Name: wilson3d
Version: 0.4.1
Summary: Tool to create animation files for Wilson
Author-email: Tobias Kerscher <88444139+tkerscher@users.noreply.github.com>
License: MIT
Project-URL: Home, https://github.com/tkerscher/wilson
Keywords: 3D,visualization
Classifier: License :: OSI Approved :: MIT License
Classifier: Programming Language :: Python
Classifier: Programming Language :: Python :: 3
Classifier: Development Status :: 4 - Beta
Requires-Python: >=3.8
License-File: LICENSE
Requires-Dist: cmasher
Requires-Dist: numpy (>=1.2.0)
Requires-Dist: protobuf (>=3.20.1)
Provides-Extra: dev
Requires-Dist: black (>=21.0) ; extra == 'dev'
Requires-Dist: mypy (>=0.950) ; extra == 'dev'
Requires-Dist: types-protobuf (>=3.20) ; extra == 'dev'
